design/tick_divider/tick_divider.v
module tick_divider #(parameter TICK_DIV = 6)(input clk,
                                              input rst,
                                              output reg tick_en
                                             );
  
  reg [($clog2(TICK_DIV))-1:0] count;
  
  always@(posedge clk) begin
    if(rst) begin
      count <= 0;
      tick_en <= 0;
    end
    else if(count == TICK_DIV-1) begin
      count <= 0;
      tick_en <= 1'b1;
    end
    else begin
      count <= count + 1;
      tick_en <= 1'b0;
    end
  end
  
endmodule

digital_stopwatch.v
`include "tick_divider/tick_divider.v"
module digital_stopwatch #(parameter TICK_DIV = 10^4)(input clk,
                 input rst,
                 input start_stop,
                 input lap,
                 input clear,
                 output reg running,
                 output reg lap_active,
                 output reg [15:0] time_count,
                 output reg [15:0] lap_count,
                 output reg [1:0] state_dbg
                );
  
  wire tick_en;
  
  tick_divider #(.TICK_DIV(TICK_DIV)) tdr(.clk(clk),
                                          .rst(rst),
                                          .tick_en(tick_en)
                                         );
  
  reg [1:0] state, nxt_state;
  
  localparam [1:0] S_STOPPED = 2'b00,
  				   S_RUNNING = 2'b01,
  				   S_LAP_HELD = 2'b10;
  
  //state transition
  
  always@(posedge clk) begin
    if(rst)
      state <= S_STOPPED;
    else if(tick_en)
      state <= nxt_state;
  end
  
  //transition logic
  
  always@(*) begin
    case(state)
      S_STOPPED: 
        begin
          if(start_stop)
            nxt_state = S_RUNNING;
          else
            nxt_state = S_STOPPED;
        end
      
      S_RUNNING: 
        begin
          if(!start_stop)
            nxt_state = S_STOPPED;
          else if(lap)
            nxt_state = S_LAP_HELD;
          else
            nxt_state = S_RUNNING;
        end
      
      S_LAP_HELD:
        begin
          if(!start_stop)
            nxt_state = S_STOPPED;
          else if(!lap)
            nxt_state = S_RUNNING;
        end
      
      default: begin
        nxt_state = S_STOPPED;
      end
    endcase
  end
  
  //counter
  always@(posedge clk) begin
    if(rst| clear) begin
      time_count <= 16'd0;
      lap_count <= 16'd0;
    end
    else if(running && tick_en) begin
      time_count <= time_count + 1;
    end
  end
  
  //output logic
  always@(*) begin
    if(state == S_STOPPED) begin
      state_dbg = S_STOPPED;
      running = 0;
      lap_active = 0;
      time_count = 0;
      lap_count = 0;
    end
    else if(state == S_RUNNING) begin
      state_dbg = S_RUNNING;
      running = 1;
      lap_active = 0;
      lap_count = 0;
    end
    else if(state == S_LAP_HELD) begin
      state_dbg = S_LAP_HELD;
      running = 1;
      lap_active = 1;
      lap_count = time_count;
    end
    else begin
      state_dbg = 2'b11; //invalid state
      running = 0;
      lap_active = 0;
    end
  end
  
  
endmodule

tb_digital_stopwatch.v
module digital_stopwatch_tb #(parameter TICK_DIV = 4)();
  reg clk,rst,start_stop,lap,clear;
  wire running, lap_active;
  wire [15:0] time_count, lap_count;
  wire [1:0] state_dbg;
  
  
  //DUT instantiation
  digital_stopwatch #(.TICK_DIV(TICK_DIV)) DUT(.clk(clk),
                .rst(rst),
                .start_stop(start_stop),
                .lap(lap),
                .clear(clear),
                .running(running),
                .lap_active(lap_active),
                .time_count(time_count),
                .lap_count(lap_count),
                .state_dbg(state_dbg)
               );
  
  //clk gen
  initial begin
    clk = 0;
    forever #20 clk = ~clk;
  end
  
  //task for running
  task run;
    input s;
    input l;
    input c;
    begin
      start_stop = s;
      lap = l;
      clear = c;
      repeat(10)@(posedge clk);
    end
  endtask
  
  initial begin
    $dumpfile("stopwatch.vcd");
    $dumpvars(0,digital_stopwatch_tb.DUT);
    rst = 1;
    repeat(5)@(posedge clk);
    rst = 0;
    $monitor("running = %b, state = %b, lap active =%b, clear = %b, lap_count = %b, time = %0t",DUT.running, state_dbg, lap_active, clear, lap_count, $time);
    run(1,0,0);
    run(1,0,0);
    run(1,0,1);
    run(1,0,0);
    run(1,0,0);
    run(1,1,0);
    run(0,1,0);
    $finish();
  end
      
  
endmodule

stopwatch.vcd
$date
	Tue Jun 16 00:21:57 2026
$end
$version
	Icarus Verilog
$end
$timescale
	1s
$end
$scope module digital_stopwatch_tb $end
$scope module DUT $end
$var wire 1 ! clear $end
$var wire 1 " clk $end
$var wire 1 # lap $end
$var wire 1 $ rst $end
$var wire 1 % start_stop $end
$var wire 1 & tick_en $end
$var parameter 2 ' S_LAP_HELD $end
$var parameter 2 ( S_RUNNING $end
$var parameter 2 ) S_STOPPED $end
$var parameter 32 * TICK_DIV $end
$var reg 1 + lap_active $end
$var reg 16 , lap_count [15:0] $end
$var reg 2 - nxt_state [1:0] $end
$var reg 1 . running $end
$var reg 2 / state [1:0] $end
$var reg 2 0 state_dbg [1:0] $end
$var reg 16 1 time_count [15:0] $end
$scope module tdr $end
$var wire 1 " clk $end
$var wire 1 $ rst $end
$var parameter 32 2 TICK_DIV $end
$var reg 2 3 count [1:0] $end
$var reg 1 & tick_en $end
$upscope $end
$upscope $end
$upscope $end
$enddefinitions $end
$comment Show the parameter values. $end
$dumpall
b100 2
b100 *
b0 )
b1 (
b10 '
$end
#0
$dumpvars
bx 3
bx 1
bx 0
bx /
x.
bx -
bx ,
x+
x&
x%
1$
x#
0"
x!
$end
#20
b0 -
0+
0.
b0 0
0&
b0 3
b0 /
b0 ,
b0 1
1"
#40
0"
#60
1"
#80
0"
#100
1"
#120
0"
#140
1"
#160
0"
#180
b1 3
b1 -
0!
0#
1%
0$
1"
#200
0"
#220
b10 3
1"
#240
0"
#260
b11 3
1"
#280
0"
#300
1&
b0 3
1"
#320
0"
#340
1.
b1 0
0&
b1 3
b1 /
1"
#360
0"
#380
b10 3
1"
#400
0"
#420
b11 3
1"
#440
0"
#460
1&
b0 3
1"
#480
0"
#500
0&
b1 3
b1 1
1"
#520
0"
#540
b10 3
1"
#560
0"
#580
b11 3
1"
#600
0"
#620
1&
b0 3
1"
#640
0"
#660
0&
b1 3
b10 1
1"
#680
0"
#700
b10 3
1"
#720
0"
#740
b11 3
1"
#760
0"
#780
1&
b0 3
1"
#800
0"
#820
0&
b1 3
b11 1
1"
#840
0"
#860
b10 3
1"
#880
0"
#900
b11 3
1"
#920
0"
#940
1&
b0 3
1"
#960
0"
#980
0&
b1 3
b100 1
1!
1"
#1000
0"
#1020
b0 1
b10 3
1"
#1040
0"
#1060
b11 3
1"
#1080
0"
#1100
1&
b0 3
1"
#1120
0"
#1140
0&
b1 3
1"
#1160
0"
#1180
b10 3
1"
#1200
0"
#1220
b11 3
1"
#1240
0"
#1260
1&
b0 3
1"
#1280
0"
#1300
0&
b1 3
1"
#1320
0"
#1340
b10 3
1"
#1360
0"
#1380
b11 3
0!
1"
#1400
0"
#1420
1&
b0 3
1"
#1440
0"
#1460
0&
b1 3
b1 1
1"
#1480
0"
#1500
b10 3
1"
#1520
0"
#1540
b11 3
1"
#1560
0"
#1580
1&
b0 3
1"
#1600
0"
#1620
0&
b1 3
b10 1
1"
#1640
0"
#1660
b10 3
1"
#1680
0"
#1700
b11 3
1"
#1720
0"
#1740
1&
b0 3
1"
#1760
0"
#1780
0&
b1 3
b11 1
1"
#1800
0"
#1820
b10 3
1"
#1840
0"
#1860
b11 3
1"
#1880
0"
#1900
1&
b0 3
1"
#1920
0"
#1940
0&
b1 3
b100 1
1"
#1960
0"
#1980
b10 3
1"
#2000
0"
#2020
b11 3
1"
#2040
0"
#2060
1&
b0 3
1"
#2080
0"
#2100
0&
b1 3
b101 1
1"
#2120
0"
#2140
b10 3
1"
#2160
0"
#2180
b11 3
b10 -
1#
1"
#2200
0"
#2220
1&
b0 3
1"
#2240
0"
#2260
b110 ,
1+
b10 0
0&
b1 3
b10 /
b110 1
1"
#2280
0"
#2300
b10 3
1"
#2320
0"
#2340
b11 3
1"
#2360
0"
#2380
1&
b0 3
1"
#2400
0"
#2420
b111 ,
0&
b1 3
b111 1
1"
#2440
0"
#2460
b10 3
1"
#2480
0"
#2500
b11 3
1"
#2520
0"
#2540
1&
b0 3
1"
#2560
0"
#2580
b1000 ,
0&
b1 3
b1000 1
b0 -
0%
1"
#2600
0"
#2620
b10 3
1"
#2640
0"
#2660
b11 3
1"
#2680
0"
#2700
1&
b0 3
1"
#2720
0"
#2740
b0 ,
0+
0.
b0 0
0&
b1 3
b0 /
b0 1
1"
#2760
0"
#2780
b10 3
1"
#2800
0"
#2820
b11 3
1"
#2840
0"
#2860
1&
b0 3
1"
#2880
0"
#2900
0&
b1 3
1"
#2920
0"
#2940
b10 3
1"
#2960
0"
#2980
b11 3
1"
