design/tick_divider/tick_divider.v
module tick_divider #(parameter TICK_DIV = 6)(input clk,
                                              input rst,
                                              output reg tick_en
                                             );
  
  reg [($clog2(TICK_DIV))-1:0] count;
  
  always@(posedge clk) begin
    if(rst) begin
      count <= 0;
      tick_en <= 0;
    end
    else if(count == TICK_DIV-1) begin
      count <= 0;
      tick_en <= 1'b1;
    end
    else begin
      count <= count + 1;
      tick_en <= 1'b0;
    end
  end
  
endmodule

design/digital_stopwatch.v
`include "tick_divider/tick_divider.v"
//set divider parameter to 5x10^7 to make clock period 1s for fpga board of freq 50MHz
module digital_stopwatch #(parameter TICK_DIV = 4)(input clk,
                 input rst, tick_rst,
                 input start_stop,
                 input lap,
                 input clear,
                 output reg running,
                 output reg lap_active,
                 output reg [15:0] time_count,
                 output reg [15:0] lap_count,
                 output reg [1:0] state_dbg
                );

 wire tick_en;
  

  tick_divider #(.TICK_DIV(TICK_DIV)) tdr(.clk(clk),
                                          .rst(tick_rst),
                                          .tick_en(tick_en)
                                         );
  
  reg [1:0] state, nxt_state;
  
  localparam [1:0] S_STOPPED = 2'b00,
  				   S_RUNNING = 2'b01,
  				   S_LAP_HELD = 2'b10;
  
  //state transition
  always@(posedge tick_en) begin
    if(rst)
      state <= S_STOPPED;
    else
      state <= nxt_state;
  end
  
  //transition logic
  always@(*) begin
    case(state)
      S_STOPPED: 
        begin
          if(start_stop)
            nxt_state = S_RUNNING;
          else
            nxt_state = S_STOPPED;
        end
      
      S_RUNNING: 
        begin
          if(start_stop | clear)
            nxt_state = S_STOPPED;
          else if(lap)
            nxt_state = S_LAP_HELD;
          else
            nxt_state = S_RUNNING;
        end
      
      S_LAP_HELD:
        begin
          if(start_stop|clear)
            nxt_state = S_STOPPED;
          else if(lap)
            nxt_state = S_RUNNING;
          else
            nxt_state = S_LAP_HELD;
        end
      
      default: begin
        nxt_state = S_STOPPED;
      end
    endcase
  end
  
  //counter
  always@(posedge tick_en) begin
    if(rst| clear) begin
      time_count <= 16'd0;
      lap_count <= 16'd0;
    end
    else begin
      if(state == S_RUNNING && nxt_state == S_LAP_HELD) begin
      	lap_count <= time_count + 1;
      end
      if(state == S_RUNNING || nxt_state == S_LAP_HELD)
      	time_count <= time_count + 1;
    end
  end
  
  //output logic
  always@(*) begin
    state_dbg = 2'b11; //invalid state
    running = 0;
    lap_active = 0;
    case(state)
      S_STOPPED: begin
        state_dbg = S_STOPPED;
        running = 0;
        lap_active = 0;
      end
      S_RUNNING: begin
        state_dbg = S_RUNNING;
        running = 1;
        lap_active = 0;
      end
      S_LAP_HELD: begin
        state_dbg = S_LAP_HELD;
        running = 1;
        lap_active = 1;
      end
      default: begin
        state_dbg = 2'b11; //invalid state
        running = 0;
        lap_active = 0;
      end
    endcase
  end
  
endmodule

design/tb_digital_stopwatch.v
module digital_stopwatch_tb #(parameter TICK_DIV = 2)();
  reg clk,rst,tick_rst,start_stop,lap,clear;
  wire running, lap_active;
  wire [15:0] time_count, lap_count;
  wire [1:0] state_dbg;
  
  
  //DUT instantiation
  digital_stopwatch #(.TICK_DIV(TICK_DIV)) DUT(.clk(clk),
                .rst(rst),
                .tick_rst(tick_rst),
                .start_stop(start_stop),
                .lap(lap),
                .clear(clear),
                .running(running),
                .lap_active(lap_active),
                .time_count(time_count),
                .lap_count(lap_count),
                .state_dbg(state_dbg)
               );
  
  wire tick = DUT.tick_en;
  
  initial begin
    clk = 0;
    rst = 1;
    tick_rst = 1;
    start_stop = 0;
    lap = 0;
    clear = 0;
  end
  
  //clk gen
  initial begin
    forever #20 clk = ~clk;
  end
  
  task start;
    begin
      @(negedge tick);
      $display("Starting stopwatch");
      #1 start_stop = 1;
      @(posedge tick);
      #1 start_stop = 0;
    end
  endtask

  task clearing;
    begin
      @(negedge tick);
      $display("Clearing stopwatch");
      #1 clear = 1;
      @(posedge tick);
      #1 clear = 0;
    end
  endtask
  
  task lapping;
    begin
      @(negedge tick);
      $display("pressing lap button");
      #1 lap = 1;
      @(posedge tick);
      #1 lap = 0;
    end
  endtask
  
  task wait_ticks(input integer n);
    begin
      repeat(n*TICK_DIV) @(posedge clk);
    end
  endtask
  
  task test_start;
    begin
      start();
      if(state_dbg == 2'b01)
        $display("Inside running state");
      wait_ticks(5);
      lapping();
      if(state_dbg == 2'b10)
        $display("Inside lap mode");
      wait_ticks(11);
      lapping();
      if(state_dbg == 2'b01)
        $display("Inside running state");
      wait_ticks(8);
      lapping();
      if(state_dbg == 2'b10)
        $display("Inside lap mode");
      wait_ticks(11);
      clearing();
      if(state_dbg == 2'b00)
        $display("Inside idle state");
      wait_ticks(5);
    end
  endtask
  
  initial begin
    $dumpfile("stopwatch.vcd");
    $dumpvars(0,digital_stopwatch_tb.DUT);
    
    $monitor("running = %b, state = %d, lap_count = %b, time_count = %0d",DUT.running, state_dbg, lap_count, time_count);
    
    wait_ticks(5);
    tick_rst = 0;
    wait_ticks(10);
    rst = 0;
    wait_ticks(10);
    test_start();
    wait_ticks(5);
    $finish();
  end
      
  
endmodule

design/stopwatch.vcd
$date
	Wed Jun 17 05:59:27 2026
$end
$version
	Icarus Verilog
$end
$timescale
	1s
$end
$scope module digital_stopwatch_tb $end
$scope module DUT $end
$var wire 1 ! clear $end
$var wire 1 " clk $end
$var wire 1 # lap $end
$var wire 1 $ rst $end
$var wire 1 % start_stop $end
$var wire 1 & tick_rst $end
$var wire 1 ' tick_en $end
$var parameter 2 ( S_LAP_HELD $end
$var parameter 2 ) S_RUNNING $end
$var parameter 2 * S_STOPPED $end
$var parameter 32 + TICK_DIV $end
$var reg 1 , lap_active $end
$var reg 16 - lap_count [15:0] $end
$var reg 2 . nxt_state [1:0] $end
$var reg 1 / running $end
$var reg 2 0 state [1:0] $end
$var reg 2 1 state_dbg [1:0] $end
$var reg 16 2 time_count [15:0] $end
$scope module tdr $end
$var wire 1 " clk $end
$var wire 1 & rst $end
$var parameter 32 3 TICK_DIV $end
$var reg 1 4 count $end
$var reg 1 ' tick_en $end
$upscope $end
$upscope $end
$upscope $end
$enddefinitions $end
$comment Show the parameter values. $end
$dumpall
b10 3
b10 +
b0 *
b1 )
b10 (
$end
#0
$dumpvars
x4
bx 2
bx 1
bx 0
x/
b0 .
bx -
x,
x'
1&
0%
1$
0#
0"
0!
$end
#20
0'
04
1"
#40
0"
#60
1"
#80
0"
#100
1"
#120
0"
#140
1"
#160
0"
#180
1"
#200
0"
#220
1"
#240
0"
#260
1"
#280
0"
#300
1"
#320
0"
#340
1"
#360
0"
#380
0&
1"
#400
0"
#420
14
1"
#440
0"
#460
0,
0/
b0 1
b0 0
b0 -
b0 2
1'
04
1"
#480
0"
#500
0'
14
1"
#520
0"
#540
1'
04
1"
#560
0"
#580
0'
14
1"
#600
0"
#620
1'
04
1"
#640
0"
#660
0'
14
1"
#680
0"
#700
1'
04
1"
#720
0"
#740
0'
14
1"
#760
0"
#780
1'
04
1"
#800
0"
#820
0'
14
1"
#840
0"
#860
1'
04
1"
#880
0"
#900
0'
14
1"
#920
0"
#940
1'
04
1"
#960
0"
#980
0'
14
1"
#1000
0"
#1020
1'
04
1"
#1040
0"
#1060
0'
14
1"
#1080
0"
#1100
1'
04
1"
#1120
0"
#1140
0'
14
1"
#1160
0"
#1180
1'
04
0$
1"
#1200
0"
#1220
0'
14
1"
#1240
0"
#1260
1'
04
1"
#1280
0"
#1300
0'
14
1"
#1320
0"
#1340
1'
04
1"
#1360
0"
#1380
0'
14
1"
#1400
0"
#1420
1'
04
1"
#1440
0"
#1460
0'
14
1"
#1480
0"
#1500
1'
04
1"
#1520
0"
#1540
0'
14
1"
#1560
0"
#1580
1'
04
1"
#1600
0"
#1620
0'
14
1"
#1640
0"
#1660
1'
04
1"
#1680
0"
#1700
0'
14
1"
#1720
0"
#1740
1'
04
1"
#1760
0"
#1780
0'
14
1"
#1800
0"
#1820
1'
04
1"
#1840
0"
#1860
0'
14
1"
#1880
0"
#1900
1'
04
1"
#1920
0"
#1940
0'
14
1"
#1960
0"
#1980
1'
04
1"
#2000
0"
#2020
0'
14
1"
#2021
b1 .
1%
#2040
0"
#2060
1/
b1 1
b0 .
b1 0
1'
04
1"
#2061
b1 .
0%
#2080
0"
#2100
0'
14
1"
#2120
0"
#2140
b1 2
1'
04
1"
#2160
0"
#2180
0'
14
1"
#2200
0"
#2220
b10 2
1'
04
1"
#2240
0"
#2260
0'
14
1"
#2280
0"
#2300
b11 2
1'
04
1"
#2320
0"
#2340
0'
14
1"
#2360
0"
#2380
b100 2
1'
04
1"
#2400
0"
#2420
0'
14
1"
#2440
0"
#2460
b101 2
1'
04
1"
#2480
0"
#2500
0'
14
1"
#2501
b10 .
1#
#2520
0"
#2540
1,
1/
b10 1
b1 .
b10 0
b110 2
b110 -
1'
04
1"
#2541
b10 .
0#
#2560
0"
#2580
0'
14
1"
#2600
0"
#2620
b111 2
1'
04
1"
#2640
0"
#2660
0'
14
1"
#2680
0"
#2700
b1000 2
1'
04
1"
#2720
0"
#2740
0'
14
1"
#2760
0"
#2780
b1001 2
1'
04
1"
#2800
0"
#2820
0'
14
1"
#2840
0"
#2860
b1010 2
1'
04
1"
#2880
0"
#2900
0'
14
1"
#2920
0"
#2940
b1011 2
1'
04
1"
#2960
0"
#2980
0'
14
1"
#3000
0"
#3020
b1100 2
1'
04
1"
#3040
0"
#3060
0'
14
1"
#3080
0"
#3100
b1101 2
1'
04
1"
#3120
0"
#3140
0'
14
1"
#3160
0"
#3180
b1110 2
1'
04
1"
#3200
0"
#3220
0'
14
1"
#3240
0"
#3260
b1111 2
1'
04
1"
#3280
0"
#3300
0'
14
1"
#3320
0"
#3340
b10000 2
1'
04
1"
#3360
0"
#3380
0'
14
1"
#3400
0"
#3420
b10001 2
1'
04
1"
#3440
0"
#3460
0'
14
1"
#3461
b1 .
1#
#3480
0"
#3500
0,
1/
b1 1
b10 .
b1 0
1'
04
1"
#3501
b1 .
0#
#3520
0"
#3540
0'
14
1"
#3560
0"
#3580
b10010 2
1'
04
1"
#3600
0"
#3620
0'
14
1"
#3640
0"
#3660
b10011 2
1'
04
1"
#3680
0"
#3700
0'
14
1"
#3720
0"
#3740
b10100 2
1'
04
1"
#3760
0"
#3780
0'
14
1"
#3800
0"
#3820
b10101 2
1'
04
1"
#3840
0"
#3860
0'
14
1"
#3880
0"
#3900
b10110 2
1'
04
1"
#3920
0"
#3940
0'
14
1"
#3960
0"
#3980
b10111 2
1'
04
1"
#4000
0"
#4020
0'
14
1"
#4040
0"
#4060
b11000 2
1'
04
1"
#4080
0"
#4100
0'
14
1"
#4120
0"
#4140
b11001 2
1'
04
1"
#4160
0"
#4180
0'
14
1"
#4181
b10 .
1#
#4200
0"
#4220
1,
1/
b10 1
b1 .
b11010 2
b11010 -
b10 0
1'
04
1"
#4221
b10 .
0#
#4240
0"
#4260
0'
14
1"
#4280
0"
#4300
b11011 2
1'
04
1"
#4320
0"
#4340
0'
14
1"
#4360
0"
#4380
b11100 2
1'
04
1"
#4400
0"
#4420
0'
14
1"
#4440
0"
#4460
b11101 2
1'
04
1"
#4480
0"
#4500
0'
14
1"
#4520
0"
#4540
b11110 2
1'
04
1"
#4560
0"
#4580
0'
14
1"
#4600
0"
#4620
b11111 2
1'
04
1"
#4640
0"
#4660
0'
14
1"
#4680
0"
#4700
b100000 2
1'
04
1"
#4720
0"
#4740
0'
14
1"
#4760
0"
#4780
b100001 2
1'
04
1"
#4800
0"
#4820
0'
14
1"
#4840
0"
#4860
b100010 2
1'
04
1"
#4880
0"
#4900
0'
14
1"
#4920
0"
#4940
b100011 2
1'
04
1"
#4960
0"
#4980
0'
14
1"
#5000
0"
#5020
b100100 2
1'
04
1"
#5040
0"
#5060
0'
14
1"
#5080
0"
#5100
b100101 2
1'
04
1"
#5120
0"
#5140
0'
14
1"
#5141
b0 .
1!
#5160
0"
#5180
0,
0/
b0 1
b0 -
b0 2
b0 0
1'
04
1"
#5181
0!
#5200
0"
#5220
0'
14
1"
#5240
0"
#5260
1'
04
1"
#5280
0"
#5300
0'
14
1"
#5320
0"
#5340
1'
04
1"
#5360
0"
#5380
0'
14
1"
#5400
0"
#5420
1'
04
1"
#5440
0"
#5460
0'
14
1"
#5480
0"
#5500
1'
04
1"
#5520
0"
#5540
0'
14
1"
#5560
0"
#5580
1'
04
1"
#5600
0"
#5620
0'
14
1"
#5640
0"
#5660
1'
04
1"
#5680
0"
#5700
0'
14
1"
#5720
0"
#5740
1'
04
1"
#5760
0"
#5780
0'
14
1"
#5800
0"
#5820
1'
04
1"
#5840
0"
#5860
0'
14
1"
#5880
0"
#5900
1'
04
1"
#5920
0"
#5940
0'
14
1"
#5960
0"
#5980
1'
04
1"
