design/tick_divider/tick_divider.v
module tick_divider #(parameter TICK_DIV = 3)(input clk,
                                              input rst,
                                              output reg tick_en
                                             );
  
  reg [($clog2(TICK_DIV))-1:0] count;
  
  always@(posedge clk) begin
    if(rst) begin
      count <= 0;
      tick_en<=0;
    end
    else if(count == TICK_DIV-1) begin
      count <= 0;
      tick_en <= ~tick_en;
    end
    else begin
      count <= count + 1;
    end
  end
  
endmodule

design/tick_divider/tb_tick_divider.v
module tb_tick_div #(parameter TICK_DIV = 4)();
  reg clk,rst;
  wire tick_en;
  
  tick_divider #(.TICK_DIV(TICK_DIV)) DUT(.clk(clk),
                   .rst(rst),
                   .tick_en(tick_en)
                  );
  
  initial begin
    clk = 0;
    forever #10 clk = ~clk;
  end
  
  initial begin
    rst = 1;
    repeat(2)@(posedge clk);
    rst = 0;
    $dumpfile("tb.vcd");
    $dumpvars(0);
              
    #1000
    $finish();
  end
endmodule

design/tick_divider/tb.vcd
$date
	Wed Jun 17 06:10:19 2026
$end
$version
	Icarus Verilog
$end
$timescale
	1s
$end
$scope module tb_tick_div $end
$var wire 1 ! tick_en $end
$var parameter 32 " TICK_DIV $end
$var reg 1 # clk $end
$var reg 1 $ rst $end
$scope module DUT $end
$var wire 1 # clk $end
$var wire 1 $ rst $end
$var parameter 32 % TICK_DIV $end
$var reg 2 & count [1:0] $end
$var reg 1 ! tick_en $end
$upscope $end
$upscope $end
$enddefinitions $end
$comment Show the parameter values. $end
$dumpall
b100 %
b100 "
$end
#30
$dumpvars
b0 &
0$
1#
0!
$end
#40
0#
#50
b1 &
1#
#60
0#
#70
b10 &
1#
#80
0#
#90
b11 &
1#
#100
0#
#110
1!
b0 &
1#
#120
0#
#130
0!
b1 &
1#
#140
0#
#150
b10 &
1#
#160
0#
#170
b11 &
1#
#180
0#
#190
1!
b0 &
1#
#200
0#
#210
0!
b1 &
1#
#220
0#
#230
b10 &
1#
#240
0#
#250
b11 &
1#
#260
0#
#270
1!
b0 &
1#
#280
0#
#290
0!
b1 &
1#
#300
0#
#310
b10 &
1#
#320
0#
#330
b11 &
1#
#340
0#
#350
1!
b0 &
1#
#360
0#
#370
0!
b1 &
1#
#380
0#
#390
b10 &
1#
#400
0#
#410
b11 &
1#
#420
0#
#430
1!
b0 &
1#
#440
0#
#450
0!
b1 &
1#
#460
0#
#470
b10 &
1#
#480
0#
#490
b11 &
1#
#500
0#
#510
1!
b0 &
1#
#520
0#
#530
0!
b1 &
1#
#540
0#
#550
b10 &
1#
#560
0#
#570
b11 &
1#
#580
0#
#590
1!
b0 &
1#
#600
0#
#610
0!
b1 &
1#
#620
0#
#630
b10 &
1#
#640
0#
#650
b11 &
1#
#660
0#
#670
1!
b0 &
1#
#680
0#
#690
0!
b1 &
1#
#700
0#
#710
b10 &
1#
#720
0#
#730
b11 &
1#
#740
0#
#750
1!
b0 &
1#
#760
0#
#770
0!
b1 &
1#
#780
0#
#790
b10 &
1#
#800
0#
#810
b11 &
1#
#820
0#
#830
1!
b0 &
1#
#840
0#
#850
0!
b1 &
1#
#860
0#
#870
b10 &
1#
#880
0#
#890
b11 &
1#
#900
0#
#910
1!
b0 &
1#
#920
0#
#930
0!
b1 &
1#
#940
0#
#950
b10 &
1#
#960
0#
#970
b11 &
1#
#980
0#
#990
1!
b0 &
1#
#1000
0#
#1010
0!
b1 &
1#
#1020
0#
#1030
b10 &
1#
